smarthomeharmonizer/__init__.py
smarthomeharmonizer/__version__.py
smarthomeharmonizer/adapters/__init__.py
smarthomeharmonizer/adapters/base.py
smarthomeharmonizer/adapters/coffee_maker.py
smarthomeharmonizer/adapters/smart_light.py
smarthomeharmonizer/adapters/thermostat.py
smarthomeharmonizer/core/__init__.py
smarthomeharmonizer/core/app.py
smarthomeharmonizer/core/device_manager.py
smarthomeharmonizer/core/exceptions.py
smarthomeharmonizer/utils/__init__.py
smarthomeharmonizer/utils/logger.py
smarthomeharmonizer/utils/validators.py
smarthomeharmonizer-0.1.0.dist-info/licenses/LICENSE
smarthomeharmonizer-0.1.0.dist-info/METADATA
smarthomeharmonizer-0.1.0.dist-info/WHEEL
smarthomeharmonizer-0.1.0.dist-info/entry_points.txt
smarthomeharmonizer-0.1.0.dist-info/top_level.txt
smarthomeharmonizer-0.1.0.dist-info/RECORD
