Metadata-Version: 2.4
Name: smarthomeharmonizer
Version: 0.1.0
Summary: A GenAI assistant-enabled Python framework for bridging IoT devices with voice assistants
Home-page: https://github.com/cppraveen/SmartHomeHarmonizer
Author: Praveen Chinnusamy
Author-email: praveenchinnusamy@gmail.com
Project-URL: Bug Reports, https://github.com/cppraveen/SmartHomeHarmonizer/issues
Project-URL: Source, https://github.com/cppraveen/SmartHomeHarmonizer
Project-URL: Documentation, https://smarthomeharmonizer.readthedocs.io
Classifier: Development Status :: 4 - Beta
Classifier: Intended Audience :: Developers
Classifier: Intended Audience :: Science/Research
Classifier: License :: OSI Approved :: MIT License
Classifier: Programming Language :: Python :: 3
Classifier: Programming Language :: Python :: 3.8
Classifier: Programming Language :: Python :: 3.9
Classifier: Programming Language :: Python :: 3.10
Classifier: Programming Language :: Python :: 3.11
Classifier: Topic :: Home Automation
Classifier: Topic :: Scientific/Engineering
Classifier: Topic :: Scientific/Engineering :: Artificial Intelligence
Classifier: Topic :: Software Development :: Libraries :: Python Modules
Requires-Python: >=3.8
License-File: LICENSE
Requires-Dist: Flask>=2.0.0
Requires-Dist: requests>=2.25.0
Provides-Extra: dev
Requires-Dist: pytest>=7.0; extra == "dev"
Requires-Dist: pytest-cov>=4.0; extra == "dev"
Requires-Dist: pytest-flask>=1.2; extra == "dev"
Requires-Dist: flake8>=6.0; extra == "dev"
Requires-Dist: black>=23.0; extra == "dev"
Requires-Dist: mypy>=1.0; extra == "dev"
Requires-Dist: sphinx>=6.0; extra == "dev"
Requires-Dist: tox>=4.0; extra == "dev"
Dynamic: author
Dynamic: author-email
Dynamic: classifier
Dynamic: description
Dynamic: description-content-type
Dynamic: home-page
Dynamic: license-file
Dynamic: project-url
Dynamic: provides-extra
Dynamic: requires-dist
Dynamic: requires-python
Dynamic: summary
